classconvergence.py
classconvergence-1.2.dist-info/LICENSE
classconvergence-1.2.dist-info/METADATA
classconvergence-1.2.dist-info/WHEEL
classconvergence-1.2.dist-info/entry_points.txt
classconvergence-1.2.dist-info/top_level.txt
classconvergence-1.2.dist-info/RECORD
