Metadata-Version: 2.1
Name: classconvergence
Version: 1.2
Summary: Plot the class distribution as a function of iteration from a Class2D or Class3D job from RELION
Home-page: https://github.com/Guillawme/classconvergence
Author: Guillaume Gaullier
Author-email: contact@gaullier.org
License: UNKNOWN
Project-URL: Bug Reports, https://github.com/Guillawme/classconvergence/issues
Project-URL: Source, https://github.com/Guillawme/classconvergence
Keywords: cryo-EM class distribution plot visualization
Platform: UNKNOWN
Classifier: Development Status :: 5 - Production/Stable
Classifier: Intended Audience :: Science/Research
Classifier: Topic :: Scientific/Engineering
Classifier: Topic :: Scientific/Engineering :: Bio-Informatics
Classifier: Topic :: Scientific/Engineering :: Visualization
Classifier: License :: OSI Approved :: MIT License
Classifier: Programming Language :: Python :: 3
Classifier: Operating System :: OS Independent
Classifier: Environment :: Console
Classifier: Natural Language :: English
Requires-Python: >=3.9.7
License-File: LICENSE
Requires-Dist: click (>=8.0.3)
Requires-Dist: matplotlib (>=3.4.3)
Requires-Dist: starfile (>=0.4.9)
